dj_translation/__init__.py
dj_translation/apps.py
dj_translation/forms.py
dj_translation/models.py
dj_translation/__pycache__/__init__.cpython-39.pyc
dj_translation/__pycache__/apps.cpython-39.pyc
dj_translation/__pycache__/forms.cpython-39.pyc
dj_translation/__pycache__/models.cpython-39.pyc
dj_translation/static/dj_translation/css/style.css
dj_translation/static/dj_translation/js/display.js
dj_translation/static/dj_translation/js/event.js
dj_translation/static/dj_translation/js/input.js
dj_translation/static/dj_translation/js/tabs.js
dj_translation/static/dj_translation/js/translation_widget.js
dj_translation/static/dj_translation/js/utils.js
dj_translation/templates/dj_translation/dj_translation_field.html
dj_translation/templatetags/__init__.py
dj_translation/templatetags/dj_translation.py
dj_translation/templatetags/__pycache__/__init__.cpython-39.pyc
dj_translation/templatetags/__pycache__/dj_translation.cpython-39.pyc
dj_translation/tests/__init__.py
dj_translation/tests/models.py
dj_translation/tests/test_translated_field.py
dj_translation/tests/test_translated_value.py
dj_translation/tests/test_translation_form_field.py
dj_translation/tests/test_widgets.py
dj_translation/tests/__pycache__/__init__.cpython-39.pyc
dj_translation/tests/__pycache__/models.cpython-39.pyc
dj_translation/tests/__pycache__/test_translated_field.cpython-39.pyc
dj_translation/tests/__pycache__/test_translated_value.cpython-39.pyc
dj_translation/tests/__pycache__/test_translation_form_field.cpython-39.pyc
dj_translation/tests/__pycache__/test_widgets.cpython-39.pyc
example/__init__.py
example/admin.py
example/apps.py
example/forms.py
example/models.py
example/urls.py
example/views.py
example/__pycache__/__init__.cpython-39.pyc
example/__pycache__/admin.cpython-39.pyc
example/__pycache__/apps.cpython-39.pyc
example/__pycache__/forms.cpython-39.pyc
example/__pycache__/models.cpython-39.pyc
example/__pycache__/urls.cpython-39.pyc
example/__pycache__/views.cpython-39.pyc
dj_translation-1.0.5.dist-info/METADATA
dj_translation-1.0.5.dist-info/WHEEL
dj_translation-1.0.5.dist-info/top_level.txt
dj_translation-1.0.5.dist-info/RECORD
