Metadata-Version: 2.1
Name: dj-translation
Version: 1.0.5
Summary: Dj_translation supports various database backends, including PostgreSQL, MySQL, SQLite, and Oracle. Developers choose based on performance, scalability, and compatibility with their tech stack.
Home-page: https://www.example.com/
Author: Fritill Team
Author-email: dev@fritill.com
License: BSD-3-Clause  # Example license
Classifier: Environment :: Web Environment
Classifier: Framework :: Django
Classifier: Framework :: Django :: 3.2
Classifier: Framework :: Django :: 4.2
Classifier: Intended Audience :: Developers
Classifier: License :: OSI Approved :: BSD License
Classifier: Operating System :: OS Independent
Classifier: Programming Language :: Python
Classifier: Programming Language :: Python :: 3
Classifier: Programming Language :: Python :: 3 :: Only
Classifier: Programming Language :: Python :: 3.8
Classifier: Programming Language :: Python :: 3.9
Classifier: Topic :: Internet :: WWW/HTTP
Classifier: Topic :: Internet :: WWW/HTTP :: Dynamic Content
Requires-Python: >=3.8
